testcenter/__init__.py
testcenter/stc_app.py
testcenter/stc_device.py
testcenter/stc_hw.py
testcenter/stc_object.py
testcenter/stc_port.py
testcenter/stc_project.py
testcenter/stc_statistics_view.py
testcenter/stc_stream.py
testcenter/api/__init__.py
testcenter/api/stc_rest.py
testcenter/api/stc_tcl.py
testcenter/samples/__init__.py
testcenter/samples/stc_samples.py
testcenter/samples/test_config.xml
pytestcenter-3.3.0.dist-info/AUTHORS
pytestcenter-3.3.0.dist-info/LICENSE
pytestcenter-3.3.0.dist-info/METADATA
pytestcenter-3.3.0.dist-info/WHEEL
pytestcenter-3.3.0.dist-info/top_level.txt
pytestcenter-3.3.0.dist-info/RECORD
